Metadata-Version: 1.0
Name: GitRestructure
Version: 0.1
Summary: A CLI tool that helps collaborating teams restructure their git branching strategies
Home-page: UNKNOWN
Author: Josh Fischer
Author-email: josh@joshfischer.io
License: UNKNOWN
Platform: UNKNOWN
